{
    "name": "hula hoop with new circle ext",
    "description": "",
    "dependencies": {
        "device": "*",
        "sprite data revised": "github:wecodemakecode/sprite-data-revised#9ac9fce45a39965be492b9402c8c8c61c4520fbd",
        "circle ext new": "github:wecodemakecode/circle-ext-new#master"
    },
    "files": [
        "main.blocks",
        "main.ts",
        "README.md",
        "tilemap.g.jres",
        "tilemap.g.ts"
    ],
    "testFiles": [
        "test.ts"
    ],
    "targetVersions": {
        "target": "1.0.15",
        "targetId": "arcade"
    },
    "supportedTargets": [
        "arcade"
    ],
    "preferredEditor": "blocksprj"
}
